openconnect_helper.py
osx_openconnect_helper-0.6.dist-info/DESCRIPTION.rst
osx_openconnect_helper-0.6.dist-info/entry_points.txt
osx_openconnect_helper-0.6.dist-info/METADATA
osx_openconnect_helper-0.6.dist-info/metadata.json
osx_openconnect_helper-0.6.dist-info/RECORD
osx_openconnect_helper-0.6.dist-info/top_level.txt
osx_openconnect_helper-0.6.dist-info/WHEEL
