Metadata-Version: 2.0
Name: osx-openconnect-helper
Version: 0.6
Summary: Wrapper around openconnect and the system keychain
Home-page: https://github.com/mitsuhiko/osx-openconnect-helper
Author: Armin Ronacher
Author-email: armin.ronacher@active-4.com
License: BSD
Platform: UNKNOWN
Requires-Dist: Click
Requires-Dist: toml
Requires-Dist: requests
